eerah_A5/__init__.py
eerah_A5/__main__.py
eerah_A5/programs/Administration.py
eerah_A5/programs/KLetShuffle.py
eerah_A5/programs/Manhattan.py
eerah_A5/programs/MonoShuffle.py
eerah_A5/programs/RollingDice.py
eerah_A5/programs/WordCount.py
eerah_A5/programs/__init__.py
eerah_A5-0.0.47.dist-info/METADATA
eerah_A5-0.0.47.dist-info/WHEEL
eerah_A5-0.0.47.dist-info/entry_points.txt
eerah_A5-0.0.47.dist-info/top_level.txt
eerah_A5-0.0.47.dist-info/RECORD
