Metadata-Version: 2.1
Name: eerah-A5
Version: 0.0.47
Summary: Contains programs for the course Algorithmen und Programmentwicklung für die Biologische Chemie
Home-page: UNKNOWN
Author: Philipp Fischer
Author-email: fischer-philipp@gmx.net
License: UNKNOWN
Keywords: APBC2021,python3
Platform: UNKNOWN
Classifier: Programming Language :: Python :: 3
Classifier: License :: OSI Approved :: MIT License
Classifier: Operating System :: OS Independent
Requires-Python: >=3.6
Requires-Dist: numpy
Requires-Dist: pandas
